agent.py
auth.py
background_task.py
config.py
firebase_client.py
github_integration.py
input_handler.py
main.py
memory.py
project_init.py
prompts.py
proxy_agent.py
terminal_manager.py
tools.py
utils.py
aadc_cli-1.0.9.6.dist-info/licenses/LICENSE
aadc_cli-1.0.9.6.dist-info/METADATA
aadc_cli-1.0.9.6.dist-info/WHEEL
aadc_cli-1.0.9.6.dist-info/entry_points.txt
aadc_cli-1.0.9.6.dist-info/top_level.txt
aadc_cli-1.0.9.6.dist-info/RECORD
