Metadata-Version: 2.4
Name: aadc-cli
Version: 1.0.9.6
Summary: AADC - Agentic AI Developer Console. Build anything with AI.
Home-page: https://github.com/yourusername/aadc
Author: AADC Team
Author-email: AADC Team <aanshsoodofficial102@gmail.com>
License-Expression: MIT
Project-URL: Homepage, https://github.com/yourusername/aadc
Project-URL: Documentation, https://github.com/yourusername/aadc#readme
Project-URL: Repository, https://github.com/yourusername/aadc
Project-URL: Issues, https://github.com/yourusername/aadc/issues
Keywords: ai,developer,agent,cli,code-generation,github
Classifier: Development Status :: 4 - Beta
Classifier: Intended Audience :: Developers
Classifier: Programming Language :: Python :: 3.9
Classifier: Programming Language :: Python :: 3.10
Classifier: Programming Language :: Python :: 3.11
Classifier: Programming Language :: Python :: 3.12
Classifier: Topic :: Software Development :: Libraries :: Python Modules
Classifier: Topic :: Software Development :: Code Generators
Requires-Python: >=3.9
License-File: LICENSE
Requires-Dist: python-dotenv>=1.0.0
Requires-Dist: httpx>=0.25.0
Dynamic: author
Dynamic: home-page
Dynamic: license-file
Dynamic: requires-python
